README
setup.py
agents/__init__.py
agents/testfile.py
dyfotest1.egg-info/PKG-INFO
dyfotest1.egg-info/SOURCES.txt
dyfotest1.egg-info/dependency_links.txt
dyfotest1.egg-info/top_level.txt