Metadata-Version: 1.1
Name: dyfotest1
Version: 0.0.1
Summary: A product to test python package uploads.
Home-page: https://dyfolabs.com
Author: Vishal Srivastava
Author-email: vishal@dyfolabs.com
License: Free
Keywords: testpackage
Platform: UNKNOWN
Classifier: Development Status :: 4 - Beta
Classifier: Topic :: Utilities
Classifier: License :: Free For Educational Use
